docs/source/conf.py
generalized_timeseries/__init__.py
generalized_timeseries/data_generator.py
generalized_timeseries/data_processor.py
generalized_timeseries/stats_model.py
generalized_timeseries/examples/__init__.py
generalized_timeseries/examples/example_bivariate_garch.py
generalized_timeseries/examples/example_univariate_garch.py
generalized_timeseries-0.1.33.dist-info/licenses/LICENSE
tests/__init__.py
tests/test_data_generator.py
tests/test_data_generator_advanced.py
tests/test_data_processor.py
tests/test_stats_model_arima.py
tests/test_stats_model_garch.py
generalized_timeseries-0.1.33.dist-info/METADATA
generalized_timeseries-0.1.33.dist-info/WHEEL
generalized_timeseries-0.1.33.dist-info/top_level.txt
generalized_timeseries-0.1.33.dist-info/RECORD
