Metadata-Version: 2.4
Name: generalized_timeseries
Version: 0.1.33
Summary: A package for time series data processing and modeling using ARIMA and GARCH models
Author-email: Garth Mortensen <mortensengarth@hotmail.com>
License: MIT
Project-URL: Homepage, https://github.com/garthmortensen/generalized-timeseries
Classifier: Programming Language :: Python :: 3
Classifier: Programming Language :: Python :: 3.11
Classifier: Programming Language :: Python :: 3.12
Classifier: Programming Language :: Python :: 3.13
Classifier: Operating System :: OS Independent
Classifier: Development Status :: 2 - Pre-Alpha
Classifier: Framework :: Pydantic :: 2
Classifier: Framework :: Pytest
Classifier: Framework :: Sphinx
Classifier: Natural Language :: English
Requires-Python: >=3.11
License-File: LICENSE
Provides-Extra: dev
Requires-Dist: pytest==8.3.4; extra == "dev"
Requires-Dist: black==24.10.0; extra == "dev"
Requires-Dist: coverage==7.6.12; extra == "dev"
Requires-Dist: tabulate==0.9.0; extra == "dev"
Provides-Extra: docs
Requires-Dist: Sphinx==8.2.1; extra == "docs"
Requires-Dist: sphinx-rtd-theme==3.0.2; extra == "docs"
Requires-Dist: tabulate==0.9.0; extra == "docs"
Dynamic: license-file
